gmap_popular_times_scrapper/__init__.py
gmap_popular_times_scrapper/scraper.py
gmap_popular_times_scrapper-0.1.0.dist-info/METADATA
gmap_popular_times_scrapper-0.1.0.dist-info/WHEEL
gmap_popular_times_scrapper-0.1.0.dist-info/top_level.txt
gmap_popular_times_scrapper-0.1.0.dist-info/RECORD
