Metadata-Version: 2.1
Name: gmap_popular_times_scrapper
Version: 0.1.0
Summary: A library to scrape Google Maps popular times data.
Author: Mohd Talha
Author-email: kt7863250@gmail.com
Requires-Dist: selenium
